polywrap_msgpack/__init__.py
polywrap_msgpack/decoder.py
polywrap_msgpack/encoder.py
polywrap_msgpack/errors.py
polywrap_msgpack/extensions/__init__.py
polywrap_msgpack/extensions/generic_map.py
polywrap_msgpack/py.typed
polywrap_msgpack/sanitize.py
polywrap_msgpack-0.1.2.dist-info/METADATA
polywrap_msgpack-0.1.2.dist-info/WHEEL
polywrap_msgpack-0.1.2.dist-info/RECORD
