Metadata-Version: 2.1
Name: polywrap-msgpack
Version: 0.1.2
Summary: WRAP msgpack encoder/decoder
Author: Cesar
Author-email: cesar@polywrap.io
Requires-Python: >=3.10,<4.0
Classifier: Programming Language :: Python :: 3
Classifier: Programming Language :: Python :: 3.10
Classifier: Programming Language :: Python :: 3.11
Requires-Dist: msgpack (>=1.0.4,<2.0.0)
